orangeshare/__init__.py
orangeshare/__main__.py
orangeshare/config.py
orangeshare/default.ini
orangeshare/devices.py
orangeshare/notify.py
orangeshare/orangeshare
orangeshare/temp_dir.py
orangeshare/__pycache__/__init__.cpython-39.pyc
orangeshare/__pycache__/__main__.cpython-39.pyc
orangeshare/__pycache__/config.cpython-39.pyc
orangeshare/__pycache__/devices.cpython-39.pyc
orangeshare/__pycache__/notify.cpython-39.pyc
orangeshare/__pycache__/temp_dir.cpython-39.pyc
orangeshare/logo/black.bmp
orangeshare/logo/black.png
orangeshare/logo/black.svg
orangeshare/logo/gray.png
orangeshare/logo/gray.svg
orangeshare/logo/orange5.afdesign
orangeshare/logo/white.ico
orangeshare/logo/white.png
orangeshare/logo/white.svg
orangeshare/shortcuts/File.py
orangeshare/shortcuts/Text.py
orangeshare/shortcuts/__init__.py
orangeshare/shortcuts/__pycache__/File.cpython-39.pyc
orangeshare/shortcuts/__pycache__/Text.cpython-39.pyc
orangeshare/shortcuts/__pycache__/__init__.cpython-39.pyc
orangeshare/shortcuts/connected/__init__.py
orangeshare/shortcuts/connected/__pycache__/__init__.cpython-39.pyc
orangeshare/shortcuts/get_data/GetData.py
orangeshare/shortcuts/get_data/__pycache__/GetData.cpython-39.pyc
orangeshare/shortcuts/get_data/icons/clipboard_dark_mode.jpeg
orangeshare/shortcuts/get_data/icons/clipboard_dark_mode.png
orangeshare/shortcuts/get_data/icons/clipboard_light_mode.png
orangeshare/shortcuts/get_data/icons/file_dark_mode.jpeg
orangeshare/shortcuts/get_data/icons/file_dark_mode.png
orangeshare/shortcuts/get_data/icons/file_light_mode.png
orangeshare/shortcuts/handlers/clipboard.py
orangeshare/shortcuts/handlers/open.py
orangeshare/shortcuts/handlers/open_helper.py
orangeshare/shortcuts/handlers/save.py
orangeshare/shortcuts/handlers/__pycache__/clipboard.cpython-39.pyc
orangeshare/shortcuts/handlers/__pycache__/open.cpython-39.pyc
orangeshare/shortcuts/handlers/__pycache__/open_helper.cpython-39.pyc
orangeshare/shortcuts/handlers/__pycache__/save.cpython-39.pyc
orangeshare-1.7.0.dist-info/LICENSE
orangeshare-1.7.0.dist-info/METADATA
orangeshare-1.7.0.dist-info/WHEEL
orangeshare-1.7.0.dist-info/top_level.txt
orangeshare-1.7.0.dist-info/RECORD
