Metadata-Version: 2.1
Name: orangeshare
Version: 1.7.0
Summary: A small python server that accepts requests from an apple shortcut to allow sharing all sorts of media from iOS with any desktop OS
Home-page: https://github.com/Yannis4444/Orange-Share
Author: Yannis Vierkoetter
Author-email: yannis44@web.de
License: MIT
Platform: UNKNOWN
Classifier: Intended Audience :: End Users/Desktop
Classifier: License :: OSI Approved :: MIT License
Classifier: Framework :: Flask
Classifier: Natural Language :: English
Classifier: Operating System :: OS Independent
Classifier: Programming Language :: Python :: 3
Classifier: Topic :: Communications :: File Sharing
License-File: LICENSE
Requires-Dist: flask
Requires-Dist: flask-restful
Requires-Dist: pyperclip
Requires-Dist: notify-py
Requires-Dist: validators
Requires-Dist: wxpython
Requires-Dist: appdirs
Requires-Dist: Flask-BasicAuth
Requires-Dist: netifaces
Requires-Dist: pillow
Requires-Dist: werkzeug
Requires-Dist: requests
